okdmr/.gitignore
okdmr/dmrlib/__init__.py
okdmr/dmrlib/etsi/__init__.py
okdmr/dmrlib/etsi/crc/__init__.py
okdmr/dmrlib/etsi/crc/crc.py
okdmr/dmrlib/etsi/crc/crc16.py
okdmr/dmrlib/etsi/crc/crc32.py
okdmr/dmrlib/etsi/crc/crc8.py
okdmr/dmrlib/etsi/crc/crc9.py
okdmr/dmrlib/etsi/fec/__init__.py
okdmr/dmrlib/etsi/fec/bptc_196_96.py
okdmr/dmrlib/etsi/fec/fec_utils.py
okdmr/dmrlib/etsi/fec/five_bit_checksum.py
okdmr/dmrlib/etsi/fec/golay_20_8_7.py
okdmr/dmrlib/etsi/fec/hamming_13_9_3.py
okdmr/dmrlib/etsi/fec/hamming_15_11_3.py
okdmr/dmrlib/etsi/fec/hamming_16_11_4.py
okdmr/dmrlib/etsi/fec/hamming_17_12_3.py
okdmr/dmrlib/etsi/fec/hamming_7_4_3.py
okdmr/dmrlib/etsi/fec/hamming_common.py
okdmr/dmrlib/etsi/fec/quadratic_residue_16_7_6.py
okdmr/dmrlib/etsi/fec/reed_solomon_12_9_4.py
okdmr/dmrlib/etsi/fec/trellis.py
okdmr/dmrlib/etsi/fec/vbptc_128_72.py
okdmr/dmrlib/etsi/fec/vbptc_32_11.py
okdmr/dmrlib/etsi/fec/vbptc_68_28.py
okdmr/dmrlib/etsi/layer2/__init__.py
okdmr/dmrlib/etsi/layer2/burst.py
okdmr/dmrlib/etsi/layer2/elements/__init__.py
okdmr/dmrlib/etsi/layer2/elements/access_types.py
okdmr/dmrlib/etsi/layer2/elements/burst_types.py
okdmr/dmrlib/etsi/layer2/elements/crc_masks.py
okdmr/dmrlib/etsi/layer2/elements/csbk_opcodes.py
okdmr/dmrlib/etsi/layer2/elements/data_packet_formats.py
okdmr/dmrlib/etsi/layer2/elements/data_types.py
okdmr/dmrlib/etsi/layer2/elements/defined_data_formats.py
okdmr/dmrlib/etsi/layer2/elements/feature_set_ids.py
okdmr/dmrlib/etsi/layer2/elements/flcos.py
okdmr/dmrlib/etsi/layer2/elements/fragment_sequence_number.py
okdmr/dmrlib/etsi/layer2/elements/full_message_flag.py
okdmr/dmrlib/etsi/layer2/elements/lcss.py
okdmr/dmrlib/etsi/layer2/elements/preemption_power_indicator.py
okdmr/dmrlib/etsi/layer2/elements/resynchronize_flag.py
okdmr/dmrlib/etsi/layer2/elements/sap_identifier.py
okdmr/dmrlib/etsi/layer2/elements/sarq.py
okdmr/dmrlib/etsi/layer2/elements/slcos.py
okdmr/dmrlib/etsi/layer2/elements/supplementary_flag.py
ok_dmrlib-0.8.0.dist-info/METADATA
ok_dmrlib-0.8.0.dist-info/WHEEL
ok_dmrlib-0.8.0.dist-info/entry_points.txt
ok_dmrlib-0.8.0.dist-info/licenses/LICENSE
ok_dmrlib-0.8.0.dist-info/RECORD
