Metadata-Version: 2.1
Name: ok-dmrlib
Version: 0.8.0
Summary: DMR PDUs, elements, FEC and CRC library, including proprietary DMR protocols of Hytera and Motorola
Project-URL: repository, https://github.com/OK-DMR/ok-dmrlib
Author-email: Marek Sebera <marek.sebera@gmail.com>
License: AGPL-3.0
License-File: LICENSE
Keywords: dmr,etsi,ham,homebrew,hytera,mmdvm,motorola,radio
Classifier: Development Status :: 3 - Alpha
Classifier: Environment :: Console
Classifier: Framework :: Pytest
Classifier: Intended Audience :: Telecommunications Industry
Classifier: License :: OSI Approved :: GNU Affero General Public License v3 or later (AGPLv3+)
Classifier: Natural Language :: English
Classifier: Operating System :: POSIX :: Linux
Classifier: Programming Language :: Python :: 3.8
Classifier: Topic :: Communications :: Ham Radio
Classifier: Typing :: Typed
Requires-Python: >=3.8
Requires-Dist: asyncio>=3.4.0
Requires-Dist: bitarray>=2.7
Requires-Dist: dmr-kaitai>=1.0
Requires-Dist: numpy>=1.24.0
Requires-Dist: scapy>=2.4.0
Provides-Extra: pre-commit
Requires-Dist: pre-commit>=3.0.0; extra == 'pre-commit'
Provides-Extra: test
Requires-Dist: crc>=4.0.0; extra == 'test'
Requires-Dist: pytest-asyncio>=0.20.0; extra == 'test'
Requires-Dist: pytest-cov>=4.0.0; extra == 'test'
Requires-Dist: pytest>=7.0.0; extra == 'test'
